Workbook

Sheet Exhibitors
A1: # | B1: Exhibitor | C1: Maker / Team | D1: Category | E1: Location / State | F1: Notes
A2: 1 | B2: Bay Area Droid Builders | C2: Bay Area Droid builders | D2: Robotics and Automation
A3: 2 | B3: Polydact: A Flexible New Finger | C3: T. Miguel Pegues | D3: Bio Medical and Wearable
A4: 3 | B4: Control a DIY Surgery Robot Arm | C4: Chandler | D4: Bio Medical and Wearable
A5: 4 | B5: Catapult Zone | C5: Graham Smith | D5: Games and Interactive
A6: 5 | B6: Linus Tech Tips | C6: Linus Tech Tips | D6: Media and Creators
A7: 6 | B7: The World's Most Advanced Pokedex | C7: BigRig Creates | D7: Software AI and Computing
A8: 7 | B8: Drive a Combat Robot - Just 'Cuz Robotics | C8: Seth Schaffer | D8: Combat Robotics
A9: 8 | B9: Bobby+ World's Largest Mechanical Pencil | C9: Bob Seif | D9: Art Light and Sculpture
A10: 9 | B10: Musical Floppy Drives! | C10: Garrett | D10: Music and Audio
A11: 10 | B11: Camera contraptions, DIY Film and Digital Cameras | C11: Tom | D11: Cameras and Imaging
A12: 11 | B12: RAT-A2E | C12: John | D12: Robotics and Automation
A13: 12 | B13: Backyard Railroading! Ride on Model Trains | C13: JT Engineering | D13: Vehicles and Transport
... A226: 225 | B226: Rubik's Cube Computer (Qter) | C226: Henry Rovnyak | D226: Software AI and Computing

Sheet Category Landscape
A1: Category | B1: Count | C1: % of Total | D1: Bar
A2: Games and Interactive | B2: =COUNTIF(Exhibitors!D:D,A2) -> 52 | C2: =B2/$B$21 -> 0.23111111 | D2: =REPT("|",B2) -> ||||||||||||||||||||||||||||||||||||||||||||||||||||
A3: Robotics and Automation | B3: =COUNTIF(Exhibitors!D:D,A3) -> 36 | C3: =B3/$B$21 -> 0.16 | D3: =REPT("|",B3) -> ||||||||||||||||||||||||||||||||||||
A4: Art Light and Sculpture | B4: =COUNTIF(Exhibitors!D:D,A4) -> 15 | C4: =B4/$B$21 -> 0.066666667 | D4: =REPT("|",B4) -> |||||||||||||||
A5: Electronics and Hardware | B5: =COUNTIF(Exhibitors!D:D,A5) -> 12 | C5: =B5/$B$21 -> 0.053333333 | D5: =REPT("|",B5) -> ||||||||||||
A6: Software AI and Computing | B6: =COUNTIF(Exhibitors!D:D,A6) -> 12 | C6: =B6/$B$21 -> 0.053333333 | D6: =REPT("|",B6) -> ||||||||||||
A7: Combat Robotics | B7: =COUNTIF(Exhibitors!D:D,A7) -> 12 | C7: =B7/$B$21 -> 0.053333333 | D7: =REPT("|",B7) -> ||||||||||||
A8: Science and Physics | B8: =COUNTIF(Exhibitors!D:D,A8) -> 11 | C8: =B8/$B$21 -> 0.048888889 | D8: =REPT("|",B8) -> |||||||||||
A9: Rocketry Space and Aero | B9: =COUNTIF(Exhibitors!D:D,A9) -> 10 | C9: =B9/$B$21 -> 0.044444444 | D9: =REPT("|",B9) -> ||||||||||
A10: Music and Audio | B10: =COUNTIF(Exhibitors!D:D,A10) -> 10 | C10: =B10/$B$21 -> 0.044444444 | D10: =REPT("|",B10) -> ||||||||||
A11: Bio Medical and Wearable | B11: =COUNTIF(Exhibitors!D:D,A11) -> 9 | C11: =B11/$B$21 -> 0.04 | D11: =REPT("|",B11) -> |||||||||
A12: Cosplay Textiles Inflatables | B12: =COUNTIF(Exhibitors!D:D,A12) -> 8 | C12: =B12/$B$21 -> 0.035555556 | D12: =REPT("|",B12) -> ||||||||
A13: Education and STEM | B13: =COUNTIF(Exhibitors!D:D,A13) -> 7 | C13: =B13/$B$21 -> 0.031111111 | D13: =REPT("|",B13) -> |||||||
... A20: Media and Creators | B20: =COUNTIF(Exhibitors!D:D,A20) -> 2 | C20: =B20/$B$21 -> 0.0088888889 | D20: =REPT("|",B20) -> ||
A21: TOTAL | B21: =SUM(B2:B20) -> 225 | C21: =B21/B21 -> 1

Sheet Convergence Examples
A1: PRISM — CONVERGENCE EXAMPLES (proof of concept)
A2: Each row links exhibitors who don't share a category but whose technologies combine into something neither is doing alone.
A3: Prism reading: GREEN = flourishing / high-leverage, PURPLE = partial, ORANGE = stagnant, RED = cautionary.
A5: Convergence | B5: Exhibitor A | C5: Exhibitor B (+ more) | D5: The inference — what X + Y makes possible | E5: Prism | F5: Opportunity / pathway
A6: Student ground-to-space telemetry | B6: Saddleback Rocketry (Rocketry) | C6: DIY Satellite Antennas · ADSBee · Magnoplotter radar | D6: Amateur rocket & drone teams gain a shared long-range tracking + downlink stack built from surplus parts — safer, higher-altitude launches with live data. | E6: GREEN | F6: Firefly Aerospace (sponsor), Space Enterprise @ Berkeley, university aero grants
A7: Open assistive-tech suite | B7: Hear us R.O.A.R. (assistive comms) | C7: Range of Motion Device · Adaptive Tech Club · Haptic Gloves · Tactile Display | D7: A modular, open hardware kit for accessibility — communication, motion, and haptic feedback that any maker or clinic can build and adapt. | E7: GREEN | F7: Disability/accessibility grants (state + federal), medical-device partners, iFixit
A8: Distributed open manufacturing | B8: WorkCell: Autonomous 3D Printing | C8: Positron 3D · OpenCAL Layerless Printing · DIY Micro 3D Printers | D8: A networked, self-running print farm from open parts — small makers get factory-scale output without factory capital. | E8: GREEN | F8: Formlabs / Makera / Prusa (sponsors), small-business manufacturing grants
A9: AI-assisted hardware design toolchain | B9: tscircuit (electronics in React) | C9: CaDoodle CAD · Vibeengineering (hardware from a chat) | D9: Describe a board in plain language, auto-route it, get it fabbed — collapses the idea-to-PCB gap for beginners. | E9: GREEN | F9: PCBWay / Seeed Studio, dev-tool startups, Kickstarter
A10: Combat-robotics league & curriculum | B10: Tombstone BattleBot | C10: Gigabyte · Malice · Team Exile · Experimental Division (UT Austin) | D10: A standardized build-fight-teach circuit turns scattered teams into a franchise-able league with an education on-ramp. | E10: GREEN | F10: Ultimate Bots (sponsor), schools/universities, sponsorship & ticketed events
A11: Wearable AI vision stack | B11: Visionary AI Glasses | C11: CSH Caption Glasses · Auto Turret body-tracking | D11: Shared low-cost eyewear platform: real-time captions, object ID, and tracking — accessibility and AR from one open base. | E11: PURPLE | F11: Accessibility funds, AR startups, semiconductor sponsors
A12: Open electromechanical instruments | B12: Musical Floppy Drives | C12: Mechanical Pianical · Staccato 3D Piano · Lupine Acoustic Drum Machine | D12: A common standard for robotic acoustic instruments — makers compose for real mechanical hardware, not just samples. | E12: PURPLE | F12: Music-tech, education, maker-kit sales
A13: Ambient data-display platform | B13: The Stock Orb (market lamp) | C13: EnergyMe Home · go fetch Card Player | D13: One open 'ambient display' framework repurposed across finance, energy, and play — glanceable data objects for the home. | E13: ORANGE | F13: Smart-home brands, prosumer kits
A14: Backyard aerospace propulsion — caution | B14: Rocket Powered Laser | C14: Multistage rapidfire coilgun · Solar drone | D14: High-energy DIY propulsion/energy projects share safety, materials, and regulatory hurdles — powerful, but needs guardrails. | E14: RED | F14: Safety review, insurers, regulated-industry mentors
A15: Open science instrumentation | B15: X-ray Vision (crystallography) | C15: Ionic Film Diodes periodic table · Miniature Natural History Museum | D15: Low-cost open lab instruments make real science reproducible in classrooms and garages. | E15: GREEN | F15: STEM education grants, university outreach, NASA Ames
